{
    "LVcustomers":[
        {
            "busId":3,
            "coded_ean":"ZIV0040302551",
            "connectionCapacity":4.6,
            "deviceId":0,
            "exclusiveNight":false,
            "phases":[
                1
            ],
            "yearlyNetConsumption":808.0384133611702
        },
        {
            "busId":3,
            "coded_ean":"ZIV0040430331",
            "connectionCapacity":4.6,
            "deviceId":1,
            "exclusiveNight":false,
            "phases":[
                1
            ],
            "yearlyNetConsumption":0.0
        },
        {
            "busId":3,
            "coded_ean":"ZIV0040430532",
            "connectionCapacity":4.6,
            "deviceId":2,
            "exclusiveNight":false,
            "phases":[
                1
            ],
            "yearlyNetConsumption":707.7106029106033
        },
        {
            "busId":3,
            "coded_ean":"ZIV0040430537",
            "connectionCapacity":5.75,
            "deviceId":3,
            "exclusiveNight":false,
            "phases":[
                2
            ],
            "yearlyNetConsumption":587.7804573804572
        },
        {
            "busId":3,
            "coded_ean":"ZIV0040637171",
            "connectionCapacity":17.32,
            "deviceId":4,
            "exclusiveNight":false,
            "phases":[
                1,
                2,
                3
            ],
            "yearlyNetConsumption":1729.2424116424093
        },
        {
            "busId":3,
            "coded_ean":"ZIV0044842687",
            "connectionCapacity":4.6,
            "deviceId":5,
            "exclusiveNight":false,
            "phases":[
                2
            ],
            "yearlyNetConsumption":428.6918918918925
        },
        {
            "busId":3,
            "coded_ean":"ZIV0044842688",
            "connectionCapacity":4.6,
            "deviceId":6,
            "exclusiveNight":false,
            "phases":[
                1
            ],
            "yearlyNetConsumption":181.7064449064442
        },
        {
            "busId":3,
            "coded_ean":"ZIV0044842689",
            "connectionCapacity":4.6,
            "deviceId":7,
            "exclusiveNight":false,
            "phases":[
                3
            ],
            "yearlyNetConsumption":606.9299999999989
        },
        {
            "busId":3,
            "coded_ean":"ZIV0044842691",
            "connectionCapacity":4.6,
            "deviceId":8,
            "exclusiveNight":false,
            "phases":[
                1
            ],
            "yearlyNetConsumption":700.2795789473697
        },
        {
            "busId":3,
            "coded_ean":"ZIV0044842694",
            "connectionCapacity":3.45,
            "deviceId":9,
            "exclusiveNight":false,
            "phases":[
                1
            ],
            "yearlyNetConsumption":993.6149688149685
        },
        {
            "busId":3,
            "coded_ean":"ZIV0050025391",
            "connectionCapacity":3.45,
            "deviceId":10,
            "exclusiveNight":false,
            "phases":[
                2
            ],
            "yearlyNetConsumption":0.0
        }
    ],
    "solarGens":[]
}