{
    "LVcustomers":[
        {
            "busId":3,
            "coded_ean":"ZIV0044828248",
            "connectionCapacity":4.6,
            "deviceId":0,
            "exclusiveNight":false,
            "phases":[
                2
            ],
            "yearlyNetConsumption":329.4037422037419
        },
        {
            "busId":3,
            "coded_ean":"ZIV0044842405",
            "connectionCapacity":4.6,
            "deviceId":1,
            "exclusiveNight":false,
            "phases":[
                2
            ],
            "yearlyNetConsumption":606.3899999999991
        },
        {
            "busId":3,
            "coded_ean":"ZIV0044842406",
            "connectionCapacity":4.6,
            "deviceId":2,
            "exclusiveNight":false,
            "phases":[
                3
            ],
            "yearlyNetConsumption":1209.1008403361325
        },
        {
            "busId":3,
            "coded_ean":"ZIV0044842407",
            "connectionCapacity":4.6,
            "deviceId":3,
            "exclusiveNight":false,
            "phases":[
                1
            ],
            "yearlyNetConsumption":1454.6941935483874
        },
        {
            "busId":3,
            "coded_ean":"ZIV0044842408",
            "connectionCapacity":4.6,
            "deviceId":4,
            "exclusiveNight":false,
            "phases":[
                1
            ],
            "yearlyNetConsumption":549.7446985446985
        },
        {
            "busId":3,
            "coded_ean":"ZIV0044842409",
            "connectionCapacity":4.6,
            "deviceId":5,
            "exclusiveNight":false,
            "phases":[
                1
            ],
            "yearlyNetConsumption":547.2898128898124
        },
        {
            "busId":3,
            "coded_ean":"ZIV0044842410",
            "connectionCapacity":4.6,
            "deviceId":6,
            "exclusiveNight":false,
            "phases":[
                2
            ],
            "yearlyNetConsumption":1501.5424947145887
        },
        {
            "busId":3,
            "coded_ean":"ZIV0044842411",
            "connectionCapacity":4.6,
            "deviceId":7,
            "exclusiveNight":false,
            "phases":[
                3
            ],
            "yearlyNetConsumption":2141.872765072769
        },
        {
            "busId":3,
            "coded_ean":"ZIV0044842412",
            "connectionCapacity":4.6,
            "deviceId":8,
            "exclusiveNight":false,
            "phases":[
                2
            ],
            "yearlyNetConsumption":1427.72129032258
        },
        {
            "busId":3,
            "coded_ean":"ZIV0044842413",
            "connectionCapacity":4.6,
            "deviceId":9,
            "exclusiveNight":false,
            "phases":[
                2
            ],
            "yearlyNetConsumption":1112.3317894736845
        },
        {
            "busId":3,
            "coded_ean":"ZIV0044842414",
            "connectionCapacity":4.6,
            "deviceId":10,
            "exclusiveNight":false,
            "phases":[
                3
            ],
            "yearlyNetConsumption":820.78496868476
        },
        {
            "busId":3,
            "coded_ean":"ZIV0044842637",
            "connectionCapacity":4.6,
            "deviceId":11,
            "exclusiveNight":false,
            "phases":[
                1
            ],
            "yearlyNetConsumption":1717.1619450317123
        },
        {
            "busId":3,
            "coded_ean":"ZIV0044842638",
            "connectionCapacity":4.6,
            "deviceId":12,
            "exclusiveNight":false,
            "phases":[
                2
            ],
            "yearlyNetConsumption":1225.8570824524302
        },
        {
            "busId":3,
            "coded_ean":"ZIV0044842639",
            "connectionCapacity":3.45,
            "deviceId":13,
            "exclusiveNight":false,
            "phases":[
                2
            ],
            "yearlyNetConsumption":1338.6846315789473
        },
        {
            "busId":3,
            "coded_ean":"ZIV0045431487",
            "connectionCapacity":10.39,
            "deviceId":14,
            "exclusiveNight":false,
            "phases":[
                1,
                2,
                3
            ],
            "yearlyNetConsumption":2607.454393305438
        },
        {
            "busId":3,
            "coded_ean":"ZIV0045431489",
            "connectionCapacity":10.39,
            "deviceId":15,
            "exclusiveNight":false,
            "phases":[
                1,
                2,
                3
            ],
            "yearlyNetConsumption":952.6153846153834
        },
        {
            "busId":5,
            "coded_ean":"ZIV0040384406",
            "connectionCapacity":4.6,
            "deviceId":16,
            "exclusiveNight":false,
            "phases":[
                1
            ],
            "yearlyNetConsumption":675.7222453222465
        },
        {
            "busId":5,
            "coded_ean":"ZIV0044842477",
            "connectionCapacity":4.6,
            "deviceId":17,
            "exclusiveNight":false,
            "phases":[
                2
            ],
            "yearlyNetConsumption":1136.3674321503129
        },
        {
            "busId":5,
            "coded_ean":"ZIV0044844838",
            "connectionCapacity":3.45,
            "deviceId":18,
            "exclusiveNight":false,
            "phases":[
                2
            ],
            "yearlyNetConsumption":441.5448851774525
        },
        {
            "busId":5,
            "coded_ean":"ZIV0044844839",
            "connectionCapacity":4.6,
            "deviceId":19,
            "exclusiveNight":false,
            "phases":[
                2
            ],
            "yearlyNetConsumption":1137.1291139240514
        },
        {
            "busId":5,
            "coded_ean":"ZIV0044844843",
            "connectionCapacity":4.6,
            "deviceId":20,
            "exclusiveNight":false,
            "phases":[
                2
            ],
            "yearlyNetConsumption":1043.593926247289
        },
        {
            "busId":5,
            "coded_ean":"ZIV0044844844",
            "connectionCapacity":4.6,
            "deviceId":21,
            "exclusiveNight":false,
            "phases":[
                2
            ],
            "yearlyNetConsumption":1048.4736401673636
        },
        {
            "busId":5,
            "coded_ean":"ZIV0045431970",
            "connectionCapacity":10.39,
            "deviceId":22,
            "exclusiveNight":false,
            "phases":[
                1,
                2,
                3
            ],
            "yearlyNetConsumption":1933.6864864864874
        }
    ],
    "solarGens":[]
}