{
    "LVcustomers":[
        {
            "busId":4,
            "coded_ean":"ZIV0034670136",
            "connectionCapacity":3.45,
            "deviceId":0,
            "exclusiveNight":false,
            "phases":[
                1
            ],
            "yearlyNetConsumption":0.0
        },
        {
            "busId":4,
            "coded_ean":"ZIV0034810810",
            "connectionCapacity":2.3,
            "deviceId":1,
            "exclusiveNight":false,
            "phases":[
                2
            ],
            "yearlyNetConsumption":606.615
        },
        {
            "busId":4,
            "coded_ean":"ZIV0034810858",
            "connectionCapacity":4.4,
            "deviceId":2,
            "exclusiveNight":false,
            "phases":[
                1
            ],
            "yearlyNetConsumption":585.6702928870285
        },
        {
            "busId":4,
            "coded_ean":"ZIV0034810860",
            "connectionCapacity":4.4,
            "deviceId":3,
            "exclusiveNight":false,
            "phases":[
                3
            ],
            "yearlyNetConsumption":978.8535564853548
        },
        {
            "busId":4,
            "coded_ean":"ZIV0034810861",
            "connectionCapacity":4.6,
            "deviceId":4,
            "exclusiveNight":false,
            "phases":[
                1
            ],
            "yearlyNetConsumption":829.8450000000009
        },
        {
            "busId":4,
            "coded_ean":"ZIV0034810862",
            "connectionCapacity":3.3,
            "deviceId":5,
            "exclusiveNight":false,
            "phases":[
                2
            ],
            "yearlyNetConsumption":1098.383298538621
        },
        {
            "busId":4,
            "coded_ean":"ZIV0034810863",
            "connectionCapacity":4.6,
            "deviceId":6,
            "exclusiveNight":false,
            "phases":[
                1
            ],
            "yearlyNetConsumption":35.595841995842015
        },
        {
            "busId":4,
            "coded_ean":"ZIV0034810864",
            "connectionCapacity":4.6,
            "deviceId":7,
            "exclusiveNight":false,
            "phases":[
                2
            ],
            "yearlyNetConsumption":904.1164241164245
        },
        {
            "busId":4,
            "coded_ean":"ZIV0034810865",
            "connectionCapacity":3.3,
            "deviceId":8,
            "exclusiveNight":false,
            "phases":[
                1
            ],
            "yearlyNetConsumption":573.5156043956046
        },
        {
            "busId":4,
            "coded_ean":"ZIV0034810866",
            "connectionCapacity":4.4,
            "deviceId":9,
            "exclusiveNight":false,
            "phases":[
                2
            ],
            "yearlyNetConsumption":734.6844074844071
        },
        {
            "busId":4,
            "coded_ean":"ZIV0034813767",
            "connectionCapacity":4.6,
            "deviceId":10,
            "exclusiveNight":false,
            "phases":[
                3
            ],
            "yearlyNetConsumption":1334.8345263157898
        },
        {
            "busId":4,
            "coded_ean":"ZIV0034816861",
            "connectionCapacity":4.6,
            "deviceId":11,
            "exclusiveNight":false,
            "phases":[
                3
            ],
            "yearlyNetConsumption":107.10187110187063
        },
        {
            "busId":4,
            "coded_ean":"ZIV0034844605",
            "connectionCapacity":3.45,
            "deviceId":12,
            "exclusiveNight":false,
            "phases":[
                1
            ],
            "yearlyNetConsumption":1002.2730688935274
        },
        {
            "busId":4,
            "coded_ean":"ZIV0034904059",
            "connectionCapacity":1.15,
            "deviceId":13,
            "exclusiveNight":false,
            "phases":[
                1
            ],
            "yearlyNetConsumption":447.71725571725466
        },
        {
            "busId":4,
            "coded_ean":"ZIV0036291232",
            "connectionCapacity":9.9,
            "deviceId":14,
            "exclusiveNight":false,
            "phases":[
                1,
                2,
                3
            ],
            "yearlyNetConsumption":1696.5355509355534
        },
        {
            "busId":4,
            "coded_ean":"ZIV0046889451",
            "connectionCapacity":4.6,
            "deviceId":15,
            "exclusiveNight":false,
            "phases":[
                3
            ],
            "yearlyNetConsumption":349.62661122661126
        },
        {
            "busId":4,
            "coded_ean":"ZIV0046924568",
            "connectionCapacity":4.6,
            "deviceId":16,
            "exclusiveNight":false,
            "phases":[
                2
            ],
            "yearlyNetConsumption":258.87068607068625
        },
        {
            "busId":7,
            "coded_ean":"ZIV0034817058",
            "connectionCapacity":3.45,
            "deviceId":17,
            "exclusiveNight":false,
            "phases":[
                1
            ],
            "yearlyNetConsumption":618.072651356993
        },
        {
            "busId":7,
            "coded_ean":"ZIV0034817060",
            "connectionCapacity":3.45,
            "deviceId":18,
            "exclusiveNight":false,
            "phases":[
                3
            ],
            "yearlyNetConsumption":1410.908315565032
        },
        {
            "busId":7,
            "coded_ean":"ZIV0034817061",
            "connectionCapacity":3.3,
            "deviceId":19,
            "exclusiveNight":false,
            "phases":[
                1
            ],
            "yearlyNetConsumption":153.02619542619624
        },
        {
            "busId":7,
            "coded_ean":"ZIV0034817062",
            "connectionCapacity":5.75,
            "deviceId":20,
            "exclusiveNight":false,
            "phases":[
                2
            ],
            "yearlyNetConsumption":2378.993762993765
        },
        {
            "busId":7,
            "coded_ean":"ZIV0034817063",
            "connectionCapacity":1.15,
            "deviceId":21,
            "exclusiveNight":false,
            "phases":[
                2
            ],
            "yearlyNetConsumption":88.89979209979158
        },
        {
            "busId":7,
            "coded_ean":"ZIV0034817064",
            "connectionCapacity":3.45,
            "deviceId":22,
            "exclusiveNight":false,
            "phases":[
                3
            ],
            "yearlyNetConsumption":667.6091476091477
        },
        {
            "busId":7,
            "coded_ean":"ZIV0034817066",
            "connectionCapacity":4.4,
            "deviceId":23,
            "exclusiveNight":false,
            "phases":[
                1
            ],
            "yearlyNetConsumption":153.89438669438687
        },
        {
            "busId":7,
            "coded_ean":"ZIV0034817067",
            "connectionCapacity":3.45,
            "deviceId":24,
            "exclusiveNight":false,
            "phases":[
                2
            ],
            "yearlyNetConsumption":657.8906054279751
        },
        {
            "busId":7,
            "coded_ean":"ZIV0034817179",
            "connectionCapacity":4.6,
            "deviceId":25,
            "exclusiveNight":false,
            "phases":[
                2
            ],
            "yearlyNetConsumption":2503.4902325581384
        },
        {
            "busId":7,
            "coded_ean":"ZIV0034817180",
            "connectionCapacity":4.4,
            "deviceId":26,
            "exclusiveNight":false,
            "phases":[
                3
            ],
            "yearlyNetConsumption":562.9471933471932
        },
        {
            "busId":7,
            "coded_ean":"ZIV0034817182",
            "connectionCapacity":4.6,
            "deviceId":27,
            "exclusiveNight":false,
            "phases":[
                3
            ],
            "yearlyNetConsumption":799.6423728813571
        },
        {
            "busId":7,
            "coded_ean":"ZIV0034817184",
            "connectionCapacity":4.6,
            "deviceId":28,
            "exclusiveNight":false,
            "phases":[
                2
            ],
            "yearlyNetConsumption":282.91060291060313
        },
        {
            "busId":7,
            "coded_ean":"ZIV0034817185",
            "connectionCapacity":4.6,
            "deviceId":29,
            "exclusiveNight":false,
            "phases":[
                3
            ],
            "yearlyNetConsumption":388.24615384615413
        },
        {
            "busId":7,
            "coded_ean":"ZIV0034817186",
            "connectionCapacity":4.6,
            "deviceId":30,
            "exclusiveNight":false,
            "phases":[
                1
            ],
            "yearlyNetConsumption":417.3754677754677
        },
        {
            "busId":7,
            "coded_ean":"ZIV0034817187",
            "connectionCapacity":4.6,
            "deviceId":31,
            "exclusiveNight":false,
            "phases":[
                1
            ],
            "yearlyNetConsumption":1565.1738947368424
        },
        {
            "busId":7,
            "coded_ean":"ZIV0036291229",
            "connectionCapacity":10.39,
            "deviceId":32,
            "exclusiveNight":false,
            "phases":[
                1,
                2,
                3
            ],
            "yearlyNetConsumption":1592.1430353430364
        },
        {
            "busId":7,
            "coded_ean":"ZIV0046917140",
            "connectionCapacity":4.6,
            "deviceId":33,
            "exclusiveNight":false,
            "phases":[
                3
            ],
            "yearlyNetConsumption":1706.8547368421061
        },
        {
            "busId":10,
            "coded_ean":"ZIV0034790380",
            "connectionCapacity":7.7,
            "deviceId":34,
            "exclusiveNight":false,
            "phases":[
                3
            ],
            "yearlyNetConsumption":4254.99813084112
        },
        {
            "busId":10,
            "coded_ean":"ZIV0034790382",
            "connectionCapacity":6.9,
            "deviceId":35,
            "exclusiveNight":false,
            "phases":[
                3
            ],
            "yearlyNetConsumption":1563.6431654676257
        },
        {
            "busId":10,
            "coded_ean":"ZIV0034790385",
            "connectionCapacity":4.4,
            "deviceId":36,
            "exclusiveNight":false,
            "phases":[
                2
            ],
            "yearlyNetConsumption":722.0377358490562
        },
        {
            "busId":10,
            "coded_ean":"ZIV0034790662",
            "connectionCapacity":3.45,
            "deviceId":37,
            "exclusiveNight":false,
            "phases":[
                3
            ],
            "yearlyNetConsumption":1281.7217758985198
        },
        {
            "busId":10,
            "coded_ean":"ZIV0034790665",
            "connectionCapacity":2.3,
            "deviceId":38,
            "exclusiveNight":false,
            "phases":[
                3
            ],
            "yearlyNetConsumption":0.0
        },
        {
            "busId":10,
            "coded_ean":"ZIV0034790666",
            "connectionCapacity":4.4,
            "deviceId":39,
            "exclusiveNight":false,
            "phases":[
                2
            ],
            "yearlyNetConsumption":2747.735779816514
        },
        {
            "busId":10,
            "coded_ean":"ZIV0034817178",
            "connectionCapacity":4.4,
            "deviceId":40,
            "exclusiveNight":false,
            "phases":[
                3
            ],
            "yearlyNetConsumption":567.1534303534305
        },
        {
            "busId":10,
            "coded_ean":"ZIV0034817181",
            "connectionCapacity":4.6,
            "deviceId":41,
            "exclusiveNight":false,
            "phases":[
                2
            ],
            "yearlyNetConsumption":672.3983193277311
        },
        {
            "busId":10,
            "coded_ean":"ZIV0034817183",
            "connectionCapacity":5.75,
            "deviceId":42,
            "exclusiveNight":false,
            "phases":[
                2
            ],
            "yearlyNetConsumption":1333.74449339207
        },
        {
            "busId":10,
            "coded_ean":"ZIV0034844883",
            "connectionCapacity":5.75,
            "deviceId":43,
            "exclusiveNight":false,
            "phases":[
                1
            ],
            "yearlyNetConsumption":2034.2842105263142
        },
        {
            "busId":10,
            "coded_ean":"ZIV0036291225",
            "connectionCapacity":6.6,
            "deviceId":44,
            "exclusiveNight":false,
            "phases":[
                1,
                2,
                3
            ],
            "yearlyNetConsumption":2383.6790020790017
        },
        {
            "busId":10,
            "coded_ean":"ZIV0036291226",
            "connectionCapacity":10.39,
            "deviceId":45,
            "exclusiveNight":false,
            "phases":[
                1,
                2,
                3
            ],
            "yearlyNetConsumption":21114.514285714293
        },
        {
            "busId":10,
            "coded_ean":"ZIV0036384017",
            "connectionCapacity":5.75,
            "deviceId":46,
            "exclusiveNight":false,
            "phases":[
                3
            ],
            "yearlyNetConsumption":2204.2494915254247
        },
        {
            "busId":18,
            "coded_ean":"ZIV0034840323",
            "connectionCapacity":3.45,
            "deviceId":47,
            "exclusiveNight":false,
            "phases":[
                2
            ],
            "yearlyNetConsumption":2432.816202531645
        },
        {
            "busId":18,
            "coded_ean":"ZIV0034938108",
            "connectionCapacity":4.6,
            "deviceId":48,
            "exclusiveNight":false,
            "phases":[
                1
            ],
            "yearlyNetConsumption":1476.633333333334
        },
        {
            "busId":18,
            "coded_ean":"ZIV0036292161",
            "connectionCapacity":13.2,
            "deviceId":49,
            "exclusiveNight":false,
            "phases":[
                1,
                2,
                3
            ],
            "yearlyNetConsumption":3427.7862212943623
        },
        {
            "busId":18,
            "coded_ean":"ZIV0036292162",
            "connectionCapacity":6.6,
            "deviceId":50,
            "exclusiveNight":false,
            "phases":[
                1,
                2,
                3
            ],
            "yearlyNetConsumption":966.8357588357587
        },
        {
            "busId":18,
            "coded_ean":"ZIV0036292166",
            "connectionCapacity":13.86,
            "deviceId":51,
            "exclusiveNight":false,
            "phases":[
                1,
                2,
                3
            ],
            "yearlyNetConsumption":1380.502857142857
        },
        {
            "busId":18,
            "coded_ean":"ZIV0046923373",
            "connectionCapacity":5.75,
            "deviceId":52,
            "exclusiveNight":false,
            "phases":[
                2
            ],
            "yearlyNetConsumption":1334.488120950326
        },
        {
            "busId":18,
            "coded_ean":"ZIV0046923374",
            "connectionCapacity":3.45,
            "deviceId":53,
            "exclusiveNight":false,
            "phases":[
                1
            ],
            "yearlyNetConsumption":0.014968814968814966
        },
        {
            "busId":18,
            "coded_ean":"ZIV0046923375",
            "connectionCapacity":6.9,
            "deviceId":54,
            "exclusiveNight":false,
            "phases":[
                2
            ],
            "yearlyNetConsumption":794.7870967741951
        },
        {
            "busId":18,
            "coded_ean":"ZIV0046923376",
            "connectionCapacity":6.9,
            "deviceId":55,
            "exclusiveNight":false,
            "phases":[
                1
            ],
            "yearlyNetConsumption":3896.0909698996643
        },
        {
            "busId":18,
            "coded_ean":"ZIV0046923377",
            "connectionCapacity":6.9,
            "deviceId":56,
            "exclusiveNight":false,
            "phases":[
                2
            ],
            "yearlyNetConsumption":3072.3599999999997
        },
        {
            "busId":18,
            "coded_ean":"ZIV0046923378",
            "connectionCapacity":5.75,
            "deviceId":57,
            "exclusiveNight":false,
            "phases":[
                3
            ],
            "yearlyNetConsumption":1937.732142857141
        },
        {
            "busId":18,
            "coded_ean":"ZIV0046923379",
            "connectionCapacity":4.6,
            "deviceId":58,
            "exclusiveNight":false,
            "phases":[
                3
            ],
            "yearlyNetConsumption":2086.2149688149684
        },
        {
            "busId":18,
            "coded_ean":"ZIV0046923380",
            "connectionCapacity":4.6,
            "deviceId":59,
            "exclusiveNight":false,
            "phases":[
                1
            ],
            "yearlyNetConsumption":0.0
        },
        {
            "busId":18,
            "coded_ean":"ZIV0046923381",
            "connectionCapacity":5.75,
            "deviceId":60,
            "exclusiveNight":false,
            "phases":[
                3
            ],
            "yearlyNetConsumption":1421.778199052132
        },
        {
            "busId":18,
            "coded_ean":"ZIV0046923382",
            "connectionCapacity":6.9,
            "deviceId":61,
            "exclusiveNight":false,
            "phases":[
                1
            ],
            "yearlyNetConsumption":817.2387096774187
        },
        {
            "busId":18,
            "coded_ean":"ZIV0046923453",
            "connectionCapacity":4.4,
            "deviceId":62,
            "exclusiveNight":false,
            "phases":[
                3
            ],
            "yearlyNetConsumption":1916.3244755244748
        },
        {
            "busId":18,
            "coded_ean":"ZIV0046923460",
            "connectionCapacity":5.5,
            "deviceId":63,
            "exclusiveNight":false,
            "phases":[
                2
            ],
            "yearlyNetConsumption":1844.681415929206
        },
        {
            "busId":18,
            "coded_ean":"ZIV0046923583",
            "connectionCapacity":9.2,
            "deviceId":64,
            "exclusiveNight":false,
            "phases":[
                3
            ],
            "yearlyNetConsumption":1471.6379562043826
        },
        {
            "busId":20,
            "coded_ean":"SAG0145400570",
            "connectionCapacity":5.75,
            "deviceId":65,
            "exclusiveNight":false,
            "phases":[
                3
            ],
            "yearlyNetConsumption":1052.539910313902
        },
        {
            "busId":20,
            "coded_ean":"SOG0020025667",
            "connectionCapacity":6.9,
            "deviceId":66,
            "exclusiveNight":false,
            "phases":[
                2
            ],
            "yearlyNetConsumption":3486.4851063829783
        },
        {
            "busId":20,
            "coded_ean":"ZIV0036292160",
            "connectionCapacity":6.6,
            "deviceId":67,
            "exclusiveNight":false,
            "phases":[
                1,
                2,
                3
            ],
            "yearlyNetConsumption":1272.4540540540531
        },
        {
            "busId":20,
            "coded_ean":"ZIV0040637425",
            "connectionCapacity":17.32,
            "deviceId":68,
            "exclusiveNight":false,
            "phases":[
                1,
                2,
                3
            ],
            "yearlyNetConsumption":4643.473684210542
        },
        {
            "busId":20,
            "coded_ean":"ZIV0046917241",
            "connectionCapacity":8.05,
            "deviceId":69,
            "exclusiveNight":false,
            "phases":[
                1
            ],
            "yearlyNetConsumption":1458.1754060324831
        },
        {
            "busId":20,
            "coded_ean":"ZIV0046923585",
            "connectionCapacity":5.5,
            "deviceId":70,
            "exclusiveNight":false,
            "phases":[
                1
            ],
            "yearlyNetConsumption":0.0
        },
        {
            "busId":20,
            "coded_ean":"ZIV0046923586",
            "connectionCapacity":6.9,
            "deviceId":71,
            "exclusiveNight":false,
            "phases":[
                3
            ],
            "yearlyNetConsumption":1947.8879999999986
        },
        {
            "busId":20,
            "coded_ean":"ZIV0046923587",
            "connectionCapacity":4.6,
            "deviceId":72,
            "exclusiveNight":false,
            "phases":[
                2
            ],
            "yearlyNetConsumption":1418.547272727274
        },
        {
            "busId":20,
            "coded_ean":"ZIV0046923588",
            "connectionCapacity":5.75,
            "deviceId":73,
            "exclusiveNight":false,
            "phases":[
                2
            ],
            "yearlyNetConsumption":2567.4403846153828
        },
        {
            "busId":20,
            "coded_ean":"ZIV0046923589",
            "connectionCapacity":4.4,
            "deviceId":74,
            "exclusiveNight":false,
            "phases":[
                2
            ],
            "yearlyNetConsumption":2725.847088607594
        },
        {
            "busId":20,
            "coded_ean":"ZIV0046923590",
            "connectionCapacity":4.4,
            "deviceId":75,
            "exclusiveNight":false,
            "phases":[
                3
            ],
            "yearlyNetConsumption":4594.692857142853
        },
        {
            "busId":20,
            "coded_ean":"ZIV0046923591",
            "connectionCapacity":3.45,
            "deviceId":76,
            "exclusiveNight":false,
            "phases":[
                3
            ],
            "yearlyNetConsumption":1808.557627118644
        },
        {
            "busId":20,
            "coded_ean":"ZIV0046923592",
            "connectionCapacity":4.6,
            "deviceId":77,
            "exclusiveNight":false,
            "phases":[
                2
            ],
            "yearlyNetConsumption":2499.9941605839435
        }
    ],
    "solarGens":[]
}