{
    "LVcustomers":[
        {
            "busId":4,
            "coded_ean":"ZIV0046160668",
            "connectionCapacity":27.71,
            "deviceId":0,
            "exclusiveNight":false,
            "phases":[
                1,
                2,
                3
            ],
            "yearlyNetConsumption":4975.598697068428
        },
        {
            "busId":5,
            "coded_ean":"ZIV0045435419",
            "connectionCapacity":10.39,
            "deviceId":1,
            "exclusiveNight":false,
            "phases":[
                1,
                2,
                3
            ],
            "yearlyNetConsumption":1015.2748440748439
        },
        {
            "busId":5,
            "coded_ean":"ZIV0046160664",
            "connectionCapacity":27.71,
            "deviceId":2,
            "exclusiveNight":false,
            "phases":[
                1,
                2,
                3
            ],
            "yearlyNetConsumption":67816.42105263159
        },
        {
            "busId":8,
            "coded_ean":"ZIV0045434536",
            "connectionCapacity":13.2,
            "deviceId":3,
            "exclusiveNight":false,
            "phases":[
                1,
                2,
                3
            ],
            "yearlyNetConsumption":6470.19497487437
        },
        {
            "busId":8,
            "coded_ean":"ZIV0045434538",
            "connectionCapacity":9.9,
            "deviceId":4,
            "exclusiveNight":false,
            "phases":[
                1,
                2,
                3
            ],
            "yearlyNetConsumption":2440.169585253456
        },
        {
            "busId":8,
            "coded_ean":"ZIV0045774950",
            "connectionCapacity":4.4,
            "deviceId":5,
            "exclusiveNight":false,
            "phases":[
                3
            ],
            "yearlyNetConsumption":1496.0571428571423
        },
        {
            "busId":8,
            "coded_ean":"ZIV0045774951",
            "connectionCapacity":4.6,
            "deviceId":6,
            "exclusiveNight":false,
            "phases":[
                1
            ],
            "yearlyNetConsumption":13.935483870967754
        },
        {
            "busId":8,
            "coded_ean":"ZIV0045774952",
            "connectionCapacity":4.4,
            "deviceId":7,
            "exclusiveNight":false,
            "phases":[
                2
            ],
            "yearlyNetConsumption":2150.477419354839
        },
        {
            "busId":8,
            "coded_ean":"ZIV0045774953",
            "connectionCapacity":4.4,
            "deviceId":8,
            "exclusiveNight":false,
            "phases":[
                3
            ],
            "yearlyNetConsumption":1635.3680672268913
        },
        {
            "busId":8,
            "coded_ean":"ZIV0045774954",
            "connectionCapacity":4.6,
            "deviceId":9,
            "exclusiveNight":false,
            "phases":[
                1
            ],
            "yearlyNetConsumption":1237.9943661971834
        },
        {
            "busId":8,
            "coded_ean":"ZIV0045774955",
            "connectionCapacity":2.3,
            "deviceId":10,
            "exclusiveNight":false,
            "phases":[
                2
            ],
            "yearlyNetConsumption":0.0
        },
        {
            "busId":8,
            "coded_ean":"ZIV0045774956",
            "connectionCapacity":3.45,
            "deviceId":11,
            "exclusiveNight":false,
            "phases":[
                2
            ],
            "yearlyNetConsumption":0.0
        },
        {
            "busId":8,
            "coded_ean":"ZIV0045774957",
            "connectionCapacity":4.6,
            "deviceId":12,
            "exclusiveNight":false,
            "phases":[
                3
            ],
            "yearlyNetConsumption":0.0
        },
        {
            "busId":8,
            "coded_ean":"ZIV0045774958",
            "connectionCapacity":4.6,
            "deviceId":13,
            "exclusiveNight":false,
            "phases":[
                2
            ],
            "yearlyNetConsumption":1231.1999999999994
        },
        {
            "busId":8,
            "coded_ean":"ZIV0046160047",
            "connectionCapacity":17.32,
            "deviceId":14,
            "exclusiveNight":false,
            "phases":[
                1,
                2,
                3
            ],
            "yearlyNetConsumption":1083.1479069767443
        },
        {
            "busId":11,
            "coded_ean":"ZIV0045434743",
            "connectionCapacity":9.9,
            "deviceId":15,
            "exclusiveNight":false,
            "phases":[
                1,
                2,
                3
            ],
            "yearlyNetConsumption":3394.1010438413336
        },
        {
            "busId":11,
            "coded_ean":"ZIV0045774500",
            "connectionCapacity":4.6,
            "deviceId":16,
            "exclusiveNight":false,
            "phases":[
                3
            ],
            "yearlyNetConsumption":27.970506912442417
        },
        {
            "busId":11,
            "coded_ean":"ZIV0045774501",
            "connectionCapacity":4.4,
            "deviceId":17,
            "exclusiveNight":false,
            "phases":[
                1
            ],
            "yearlyNetConsumption":728.2000000000003
        },
        {
            "busId":11,
            "coded_ean":"ZIV0045774553",
            "connectionCapacity":3.45,
            "deviceId":18,
            "exclusiveNight":false,
            "phases":[
                2
            ],
            "yearlyNetConsumption":705.4333333333329
        },
        {
            "busId":11,
            "coded_ean":"ZIV0045774554",
            "connectionCapacity":4.4,
            "deviceId":19,
            "exclusiveNight":false,
            "phases":[
                2
            ],
            "yearlyNetConsumption":1459.14470046083
        },
        {
            "busId":11,
            "coded_ean":"ZIV0045774869",
            "connectionCapacity":4.6,
            "deviceId":20,
            "exclusiveNight":false,
            "phases":[
                1
            ],
            "yearlyNetConsumption":1436.7364485981325
        },
        {
            "busId":11,
            "coded_ean":"ZIV0045777245",
            "connectionCapacity":4.6,
            "deviceId":21,
            "exclusiveNight":false,
            "phases":[
                1
            ],
            "yearlyNetConsumption":1861.8171428571422
        },
        {
            "busId":11,
            "coded_ean":"ZIV0045777246",
            "connectionCapacity":4.4,
            "deviceId":22,
            "exclusiveNight":false,
            "phases":[
                2
            ],
            "yearlyNetConsumption":1389.4260869565214
        },
        {
            "busId":11,
            "coded_ean":"ZIV0045777247",
            "connectionCapacity":4.6,
            "deviceId":23,
            "exclusiveNight":false,
            "phases":[
                3
            ],
            "yearlyNetConsumption":955.6056338028169
        },
        {
            "busId":11,
            "coded_ean":"ZIV0045777252",
            "connectionCapacity":4.6,
            "deviceId":24,
            "exclusiveNight":false,
            "phases":[
                1
            ],
            "yearlyNetConsumption":945.464788732394
        },
        {
            "busId":11,
            "coded_ean":"ZIV0045777256",
            "connectionCapacity":4.4,
            "deviceId":25,
            "exclusiveNight":false,
            "phases":[
                3
            ],
            "yearlyNetConsumption":672.4202764976959
        },
        {
            "busId":11,
            "coded_ean":"ZIV0045777284",
            "connectionCapacity":4.6,
            "deviceId":26,
            "exclusiveNight":false,
            "phases":[
                2
            ],
            "yearlyNetConsumption":1005.1465437788017
        },
        {
            "busId":11,
            "coded_ean":"ZIV0045777460",
            "connectionCapacity":4.6,
            "deviceId":27,
            "exclusiveNight":false,
            "phases":[
                3
            ],
            "yearlyNetConsumption":495.2073732718893
        },
        {
            "busId":11,
            "coded_ean":"ZIV0045777463",
            "connectionCapacity":4.6,
            "deviceId":28,
            "exclusiveNight":false,
            "phases":[
                3
            ],
            "yearlyNetConsumption":1749.1521531100486
        },
        {
            "busId":11,
            "coded_ean":"ZIV0045777464",
            "connectionCapacity":4.4,
            "deviceId":29,
            "exclusiveNight":false,
            "phases":[
                2
            ],
            "yearlyNetConsumption":1565.4295081967216
        }
    ],
    "solarGens":[]
}